lmd/__init__.py
lmd/_utils.py
lmd/conftest.py
lmd/lib.py
lmd/segmentation.py
lmd/tools.py
py_lmd-1.5.0.dist-info/licenses/LICENSE
py_lmd-1.5.0.dist-info/METADATA
py_lmd-1.5.0.dist-info/WHEEL
py_lmd-1.5.0.dist-info/top_level.txt
py_lmd-1.5.0.dist-info/RECORD
