Metadata-Version: 2.4
Name: py-lmd
Version: 1.5.0
Summary: Read, Modify and Create new shape files for the Leica LMD6 & LMD7
Author: Georg Wallmann, Niklas Schmacke, Lucas Diedrich
Author-email: Sophia Maedler <hello@sophia-maedler.com>
Maintainer-email: Sophia Maedler <hello@sophia-maedler.com>, Lucas Diedrich <wallmann@biochem.mpg.de>, Georg Wallmann <wallmann@biochem.mpg.de>
License:                                  Apache License
Project-URL: Homepage, https://github.com/MannLabs/py-lmd
Project-URL: Documentation, https://mannlabs.github.io/py-lmd/html/index.html
Project-URL: Source, https://github.com/MannLabs/py-lmd
Keywords: LMD
Classifier: License :: OSI Approved :: Apache Software License
Classifier: Programming Language :: Python
Classifier: Intended Audience :: Science/Research
Classifier: Natural Language :: English
Classifier: Operating System :: OS Independent
Classifier: Topic :: Scientific/Engineering :: Bio-Informatics
Requires-Python: >=3.9
License-File: LICENSE
Requires-Dist: numpy<=2.1.0
Requires-Dist: matplotlib
Requires-Dist: lxml
Requires-Dist: networkx>=3.1
Requires-Dist: scikit-image>=0.19
Requires-Dist: svgelements
Requires-Dist: setuptools
Requires-Dist: numba
Requires-Dist: tqdm
Requires-Dist: hilbertcurve
Requires-Dist: requests
Requires-Dist: filelock
Requires-Dist: geopandas
Requires-Dist: shapely
Requires-Dist: rdp
Provides-Extra: dev-only
Requires-Dist: pre-commit; extra == "dev-only"
Provides-Extra: doc
Requires-Dist: pre-commit; extra == "doc"
Requires-Dist: sphinx; extra == "doc"
Requires-Dist: sphinx-argparse; extra == "doc"
Requires-Dist: sphinx-rtd-theme==2.0.0; extra == "doc"
Requires-Dist: nbsphinx; extra == "doc"
Requires-Dist: sphinx_book_theme; extra == "doc"
Requires-Dist: sphinx-copybutton; extra == "doc"
Requires-Dist: geojson; extra == "doc"
Requires-Dist: pytest; extra == "doc"
Provides-Extra: test
Requires-Dist: pre-commit; extra == "test"
Requires-Dist: pytest; extra == "test"
Provides-Extra: dev
Requires-Dist: pre-commit; extra == "dev"
Requires-Dist: pre-commit; extra == "dev"
Requires-Dist: pytest; extra == "dev"
Dynamic: license-file
